tyba_NREL_PySAM.libs/libssc-a6aac9f7.so
PySAM/TestUdPowerCycle.cpython-36m-aarch64-linux-gnu.so
PySAM/Sco2AirCooler.pyi
PySAM/UiTesCalcs.pyi
PySAM/Pvwattsv1Poa.cpython-36m-aarch64-linux-gnu.so
PySAM/Merchantplant.pyi
PySAM/Annualoutput.cpython-36m-aarch64-linux-gnu.so
PySAM/Communitysolar.pyi
PySAM/SixParsolve.pyi
PySAM/Utilityrate3.cpython-36m-aarch64-linux-gnu.so
PySAM/Pvwattsv5.pyi
PySAM/Levpartflip.pyi
PySAM/Pvwattsv51ts.cpython-36m-aarch64-linux-gnu.so
PySAM/Cashloan.cpython-36m-aarch64-linux-gnu.so
PySAM/CbEmpiricalHceHeatLoss.cpython-36m-aarch64-linux-gnu.so
PySAM/GenericSystem.cpython-36m-aarch64-linux-gnu.so
PySAM/Singleowner.cpython-36m-aarch64-linux-gnu.so
PySAM/Windcsm.cpython-36m-aarch64-linux-gnu.so
PySAM/Utilityrateforecast.cpython-36m-aarch64-linux-gnu.so
PySAM/EtesPtes.cpython-36m-aarch64-linux-gnu.so
PySAM/TroughPhysicalCspSolver.pyi
PySAM/Singlediode.pyi
PySAM/TcslinearFresnel.pyi
PySAM/Poacalib.pyi
PySAM/TcsgenericSolar.cpython-36m-aarch64-linux-gnu.so
PySAM/Pvwattsv51ts.pyi
PySAM/Pvwattsv1Poa.pyi
PySAM/TroughPhysical.pyi
PySAM/AdjustmentFactors.pyi
PySAM/Fuelcell.pyi
PySAM/MhkCosts.pyi
PySAM/Utilityrate.pyi
PySAM/LinearFresnelDsgIph.cpython-36m-aarch64-linux-gnu.so
PySAM/Pvwattsv8.pyi
PySAM/Thermalrate.pyi
PySAM/version.py
PySAM/CbEmpiricalHceHeatLoss.pyi
PySAM/MsptSfAndRecIsolated.cpython-36m-aarch64-linux-gnu.so
PySAM/__init__.py
PySAM/CspDsgLfUi.cpython-36m-aarch64-linux-gnu.so
PySAM/Hcpv.cpython-36m-aarch64-linux-gnu.so
PySAM/TcsmoltenSalt.pyi
PySAM/Annualoutput.pyi
PySAM/Snowmodel.pyi
PySAM/GenericSystem.pyi
PySAM/Wfreader.cpython-36m-aarch64-linux-gnu.so
PySAM/TroughPhysical.cpython-36m-aarch64-linux-gnu.so
PySAM/Swh.pyi
PySAM/Thirdpartyownership.pyi
PySAM/UserHtfComparison.pyi
PySAM/TcslinearFresnel.cpython-36m-aarch64-linux-gnu.so
PySAM/Battwatts.pyi
PySAM/Communitysolar.cpython-36m-aarch64-linux-gnu.so
PySAM/Wfcsvconv.pyi
PySAM/Pv6parmod.cpython-36m-aarch64-linux-gnu.so
tyba_NREL_PySAM-3.0.2.dist-info/top_level.txt
tyba_NREL_PySAM-3.0.2.dist-info/RECORD
tyba_NREL_PySAM-3.0.2.dist-info/LICENSE
tyba_NREL_PySAM-3.0.2.dist-info/METADATA
tyba_NREL_PySAM-3.0.2.dist-info/WHEEL
