Metadata-Version: 2.1
Name: tyba-NREL-PySAM
Version: 3.0.2
Summary: National Renewable Energy Laboratory's System Advisor Model Python Wrapper
Home-page: https://nrel-pysam.readthedocs.io
Author: dguittet
Author-email: dguittet@nrel.gov
License: BSD 3-Clause
Platform: UNKNOWN
License-File: LICENSE
Requires-Dist: pandas
Requires-Dist: python-dotenv
Requires-Dist: requests
